MANIFEST.in
README.md
setup.py
bin/lanas
kanzen/kanzen/__init__.py
kanzen/kanzen/__init__.pyc
kanzen/kanzen/analyzer.py
kanzen/kanzen/analyzer.pyc
kanzen/kanzen/code_completion.py
kanzen/kanzen/code_completion.pyc
kanzen/kanzen/completer.py
kanzen/kanzen/completer.pyc
kanzen/kanzen/completion_daemon.py
kanzen/kanzen/completion_daemon.pyc
kanzen/kanzen/model.py
kanzen/kanzen/model.pyc
kanzen/kanzen/utils.py
kanzen/kanzen/utils.pyc
lanas/__init__.py
lanas/autocomplete.py
lanas/highlighter.py
lanas/interprete.py
lanas/lanas.py
lanas/version.py
lanas.egg-info/PKG-INFO
lanas.egg-info/SOURCES.txt
lanas.egg-info/dependency_links.txt
lanas.egg-info/requires.txt
lanas.egg-info/top_level.txt