Metadata-Version: 1.0
Name: lanas
Version: 0.2.1
Summary: Una consola sencilla de python
Home-page: https://github.com/hugoruscitti/lanas
Author: Hugo Ruscitti
Author-email: hugoruscitti@gmail.com
License: UNKNOWN
Platform: UNKNOWN
